MANIFEST.in
README.md
requirements.txt
setup.py
Triple.egg-info/PKG-INFO
Triple.egg-info/SOURCES.txt
Triple.egg-info/dependency_links.txt
Triple.egg-info/entry_points.txt
Triple.egg-info/not-zip-safe
Triple.egg-info/requires.txt
Triple.egg-info/top_level.txt
triple/__init__.py
triple/__main__.py
triple/_cmd_.py
triple/server.py
triple/config/ports.txt
triple/config/script.js
triple/config/settings.json